Workbook

Sheet Assumptions
A1: Cost-of-Turnover Model — Assumptions
A3: Parameter | B3: Value | C3: Unit / format | D3: Rationale
A4: HighRiskThreshold | B4: 0.45 | C4: probability (0–1) | D4: Employees with model P(attrition) ≥ this value are flagged for intervention. Aligned with the modeling High risk tier cutoff (0.45).
A5: RetentionEffectiveness | B5: 0.42 | C5: share of expected leavers retained (0–1) | D5: Share of expected departures among flagged employees that a targeted retention program is assumed to prevent (workload review, manager check-in, selective retention actions).
A6: ReplacementCostPct | B6: 1.5 | C6: × annual salary | D6: Fully loaded replacement cost as a multiple of annual salary (recruiting, onboarding, ramp-down/ramp-up productivity loss). 150% is a mid-range professional/knowledge-worker benchmark.
A7: MonthsPerYear | B7: 12 | C7: months | D7: Converts monthly_income from the HR extract to annual salary.
A9: How projected savings are calculated
A10: For each flagged current employee i: ExpectedSavings_i = AttritionProbability_i × RetentionEffectiveness × ReplacementCostPct × AnnualSalary_i. Projected program savings = SUM of ExpectedSavings_i over flagged employees (see Cost Model sheet). All summary metrics are Excel formulas referencing these yellow input cells — change assumptions and the savings figure updates.
A14: Data sources
A15: Current employees: attrition = No in data/processed/employee_attrition_clean.csv. Probabilities / risk tiers: data/processed/employee_risk_scores.csv (XGBoost).

Sheet At-Risk
A1: EmployeeNumber | B1: Department | C1: JobRole | D1: OverTime | E1: MonthlyIncome | F1: AnnualSalary | G1: AttritionProbability | H1: RiskTier | I1: Flagged | J1: ReplacementCost | K1: ExpectedCostIfNoIntervention | L1: ExpectedSavingsIfRetained
A2: 411 | B2: Sales | C2: Sales Representative | D2: No | E2: 1200 | F2: =E2*Assumptions!$B$7 | G2: 0.9595 | H2: High | I2: =IF(G2>=Assumptions!$B$4,"Yes","No") | J2: =F2*Assumptions!$B$6 | K2: =G2*J2 | L2: =IF(I2="Yes",G2*Assumptions!$B$5*J2,0)
A3: 2021 | B3: Sales | C3: Sales Representative | D3: Yes | E3: 2380 | F3: =E3*Assumptions!$B$7 | G3: 0.8948 | H3: High | I3: =IF(G3>=Assumptions!$B$4,"Yes","No") | J3: =F3*Assumptions!$B$6 | K3: =G3*J3 | L3: =IF(I3="Yes",G3*Assumptions!$B$5*J3,0)
A4: 1974 | B4: Research & Development | C4: Laboratory Technician | D4: Yes | E4: 1129 | F4: =E4*Assumptions!$B$7 | G4: 0.8877 | H4: High | I4: =IF(G4>=Assumptions!$B$4,"Yes","No") | J4: =F4*Assumptions!$B$6 | K4: =G4*J4 | L4: =IF(I4="Yes",G4*Assumptions!$B$5*J4,0)
A5: 1056 | B5: Sales | C5: Sales Representative | D5: No | E5: 1052 | F5: =E5*Assumptions!$B$7 | G5: 0.796 | H5: High | I5: =IF(G5>=Assumptions!$B$4,"Yes","No") | J5: =F5*Assumptions!$B$6 | K5: =G5*J5 | L5: =IF(I5="Yes",G5*Assumptions!$B$5*J5,0)
A6: 643 | B6: Research & Development | C6: Laboratory Technician | D6: No | E6: 2127 | F6: =E6*Assumptions!$B$7 | G6: 0.72 | H6: High | I6: =IF(G6>=Assumptions!$B$4,"Yes","No") | J6: =F6*Assumptions!$B$6 | K6: =G6*J6 | L6: =IF(I6="Yes",G6*Assumptions!$B$5*J6,0)
A7: 1839 | B7: Research & Development | C7: Research Scientist | D7: No | E7: 1514 | F7: =E7*Assumptions!$B$7 | G7: 0.7171 | H7: High | I7: =IF(G7>=Assumptions!$B$4,"Yes","No") | J7: =F7*Assumptions!$B$6 | K7: =G7*J7 | L7: =IF(I7="Yes",G7*Assumptions!$B$5*J7,0)
A8: 833 | B8: Research & Development | C8: Manufacturing Director | D8: Yes | E8: 6877 | F8: =E8*Assumptions!$B$7 | G8: 0.669 | H8: High | I8: =IF(G8>=Assumptions!$B$4,"Yes","No") | J8: =F8*Assumptions!$B$6 | K8: =G8*J8 | L8: =IF(I8="Yes",G8*Assumptions!$B$5*J8,0)
A9: 1036 | B9: Sales | C9: Sales Executive | D9: Yes | E9: 6861 | F9: =E9*Assumptions!$B$7 | G9: 0.584 | H9: High | I9: =IF(G9>=Assumptions!$B$4,"Yes","No") | J9: =F9*Assumptions!$B$6 | K9: =G9*J9 | L9: =IF(I9="Yes",G9*Assumptions!$B$5*J9,0)
A10: 1961 | B10: Sales | C10: Sales Representative | D10: No | E10: 2858 | F10: =E10*Assumptions!$B$7 | G10: 0.5776 | H10: High | I10: =IF(G10>=Assumptions!$B$4,"Yes","No") | J10: =F10*Assumptions!$B$6 | K10: =G10*J10 | L10: =IF(I10="Yes",G10*Assumptions!$B$5*J10,0)
A11: 399 | B11: Sales | C11: Sales Representative | D11: No | E11: 2789 | F11: =E11*Assumptions!$B$7 | G11: 0.575 | H11: High | I11: =IF(G11>=Assumptions!$B$4,"Yes","No") | J11: =F11*Assumptions!$B$6 | K11: =G11*J11 | L11: =IF(I11="Yes",G11*Assumptions!$B$5*J11,0)
A12: 1646 | B12: Research & Development | C12: Research Scientist | D12: Yes | E12: 3760 | F12: =E12*Assumptions!$B$7 | G12: 0.5738 | H12: High | I12: =IF(G12>=Assumptions!$B$4,"Yes","No") | J12: =F12*Assumptions!$B$6 | K12: =G12*J12 | L12: =IF(I12="Yes",G12*Assumptions!$B$5*J12,0)
A13: 144 | B13: Research & Development | C13: Laboratory Technician | D13: No | E13: 2871 | F13: =E13*Assumptions!$B$7 | G13: 0.5697 | H13: High | I13: =IF(G13>=Assumptions!$B$4,"Yes","No") | J13: =F13*Assumptions!$B$6 | K13: =G13*J13 | L13: =IF(I13="Yes",G13*Assumptions!$B$5*J13,0)
... A1234: 997 | B1234: Research & Development | C1234: Research Director | D1234: No | E1234: 17399 | F1234: =E1234*Assumptions!$B$7 | G1234: 0.0005 | H1234: Low | I1234: =IF(G1234>=Assumptions!$B$4,"Yes","No") | J1234: =F1234*Assumptions!$B$6 | K1234: =G1234*J1234 | L1234: =IF(I1234="Yes",G1234*Assumptions!$B$5*J1234,0)

Sheet Cost Model
A1: Cost-of-Turnover Dashboard
A3: Metric | B3: Value | C3: Formula / definition
A4: Current employees (Attrition=No) | B4: =COUNTA('At-Risk'!A2:A1234) | C4: All current employees scored by the model
A5: Flagged at-risk employees | B5: =COUNTIF('At-Risk'!I2:I1234,"Yes") | C5: Count where AttritionProbability ≥ HighRiskThreshold
A6: Expected leavers without intervention | B6: =SUMIF('At-Risk'!I2:I1234,"Yes",'At-Risk'!G2:G1234) | C6: Sum of attrition probabilities among flagged employees
A7: Prevented leavers (with program) | B7: =B6*Assumptions!B5 | C7: Expected leavers × RetentionEffectiveness
A8: Avg annual salary (flagged) | B8: =AVERAGEIF('At-Risk'!I2:I1234,"Yes",'At-Risk'!F2:F1234) | C8: Average AnnualSalary among flagged rows
A9: Avg replacement cost per leaver | B9: =B8*Assumptions!B6 | C9: Avg annual salary × ReplacementCostPct
A10: Expected turnover cost (no intervention) | B10: =SUMIF('At-Risk'!I2:I1234,"Yes",'At-Risk'!K2:K1234) | C10: Sum of P(attrition) × replacement cost for flagged employees
A11: Projected savings (retention program) | B11: =SUMIF('At-Risk'!I2:I1234,"Yes",'At-Risk'!L2:L1234) | C11: Sum of P × effectiveness × replacement cost for flagged employees
A13: Assumption cross-check (linked)
A14: HighRiskThreshold | B14: =Assumptions!B4
A15: RetentionEffectiveness | B15: =Assumptions!B5
A16: ReplacementCostPct | B16: =Assumptions!B6
A18: Interpretation
A19: Among current employees flagged as high attrition risk, the model expects B6 departures in the absence of intervention. A targeted retention program assumed to retain B15 of those expected exits avoids B7 departures, each costing about B9 to replace, for projected savings of B11.
